netlens/__init__.py
netlens/attribution.py
netlens/distributions.py
netlens/quantities.py
netlens/slices.py
netlens/visualizations.py
netlens/backend/__init__.py
netlens/backend/backend.py
netlens/backend/load_backend.py
netlens/backend/keras_backend/__init__.py
netlens/backend/keras_backend/keras.py
netlens/backend/pytorch_backend/__init__.py
netlens/backend/pytorch_backend/pytorch.py
netlens/backend/tf_backend/__init__.py
netlens/backend/tf_backend/tf.py
netlens/models/__init__.py
netlens/models/_model_base.py
netlens/models/keras.py
netlens/models/pytorch.py
netlens/models/tensorflow_v1.py
netlens/models/tensorflow_v2.py
netlens-0.0.1.dist-info/LICENSE
netlens-0.0.1.dist-info/METADATA
netlens-0.0.1.dist-info/WHEEL
netlens-0.0.1.dist-info/top_level.txt
netlens-0.0.1.dist-info/RECORD
