Metadata-Version: 2.1
Name: netlens
Version: 0.0.1
Summary: Library containing attribution and interpretation methods for deep nets.
Home-page: UNKNOWN
Author: Truera Inc
Author-email: all@truera.com
License: UNKNOWN
Platform: UNKNOWN
Classifier: Programming Language :: Python :: 3
Classifier: Operating System :: OS Independent
Classifier: Development Status :: 3 - Alpha
Requires-Python: >=3.6
